buybacks2/__init__.py
buybacks2/admin.py
buybacks2/app_settings.py
buybacks2/apps.py
buybacks2/auth_hooks.py
buybacks2/constants.py
buybacks2/forms.py
buybacks2/helpers.py
buybacks2/managers.py
buybacks2/models.py
buybacks2/tasks.py
buybacks2/urls.py
buybacks2/utils.py
buybacks2/validators.py
buybacks2/management/__init__.py
buybacks2/management/commands/__init__.py
buybacks2/management/commands/buybacks_load_types.py
buybacks2/migrations/0001_initial.py
buybacks2/migrations/0002_programs.py
buybacks2/migrations/0003_contracts.py
buybacks2/migrations/__init__.py
buybacks2/static/buybacks/js/autocomplete.js
buybacks2/static/buybacks/js/bootstrap-autocomplete.min.js
buybacks2/static/buybacks/js/notify.js
buybacks2/templates/buybacks2/base.html
buybacks2/templates/buybacks2/index.html
buybacks2/templates/buybacks2/menu.html
buybacks2/templates/buybacks2/notification_edit.html
buybacks2/templates/buybacks2/notifications.html
buybacks2/templates/buybacks2/page.html
buybacks2/templates/buybacks2/program.html
buybacks2/templates/buybacks2/program_add.html
buybacks2/templates/buybacks2/program_add_item.html
buybacks2/templates/buybacks2/program_add_location.html
buybacks2/templates/buybacks2/program_calculate.html
buybacks2/templates/buybacks2/stats.html
buybacks2/templatetags/__init__.py
buybacks2/templatetags/date.py
buybacks2/templatetags/dict.py
buybacks2/templatetags/number.py
buybacks2/views/__init__.py
buybacks2/views/common.py
buybacks2/views/notifications.py
buybacks2/views/programs.py
buybacks2/views/stats.py
testauth/__init__.py
testauth/celery.py
testauth/settings.py
testauth/urls.py
testauth/wsgi.py
aa_buybacks2-0.2.1.dist-info/LICENSE
aa_buybacks2-0.2.1.dist-info/METADATA
aa_buybacks2-0.2.1.dist-info/WHEEL
aa_buybacks2-0.2.1.dist-info/top_level.txt
aa_buybacks2-0.2.1.dist-info/RECORD
