Metadata-Version: 2.1
Name: aa-buybacks2
Version: 0.2.1
Summary: Buyback program management app for Alliance Auth
Home-page: https://github.com/hullwarning/aa-buybacks
Author: Pavan Kumar Sunkara
Author-email: pavan.sss1991@gmail.com
License: MIT
Platform: UNKNOWN
Classifier: Environment :: Web Environment
Classifier: Framework :: Django
Classifier: Framework :: Django :: 3.2
Classifier: Intended Audience :: Developers
Classifier: License :: OSI Approved :: MIT License
Classifier: Operating System :: OS Independent
Classifier: Programming Language :: Python
Classifier: Programming Language :: Python :: 3.6
Classifier: Programming Language :: Python :: 3.7
Classifier: Programming Language :: Python :: 3.8
Classifier: Programming Language :: Python :: 3.9
Classifier: Programming Language :: Python :: 3.10
Classifier: Topic :: Internet :: WWW/HTTP
Classifier: Topic :: Internet :: WWW/HTTP :: Dynamic Content
Requires-Python: ~=3.6
Requires-Dist: allianceauth (>=2.9.0)
Requires-Dist: celery-once (>=2.0.1)
Requires-Dist: django-esi (>=2.0.4)
Requires-Dist: django-eveuniverse (>=0.6.1)
Requires-Dist: django-navhelper
Requires-Dist: requests
Requires-Dist: requests-cache
